http_query/__init__.py
http_query/http_query.py
jsonreq_ase-0.0.3.dist-info/METADATA
jsonreq_ase-0.0.3.dist-info/WHEEL
jsonreq_ase-0.0.3.dist-info/entry_points.txt
jsonreq_ase-0.0.3.dist-info/top_level.txt
jsonreq_ase-0.0.3.dist-info/RECORD
