Metadata-Version: 2.1
Name: jsonreq-ase
Version: 0.0.3
Summary: Dont install this package, purely testing purpose
Author: Abss
Requires-Dist: click
Requires-Dist: requests
